logger/__init__.py
logger/logger.py
logger/py.typed
simplecoloredlogs-1.16.1.2026.dist-info/licenses/LICENSE
simplecoloredlogs-1.16.1.2026.dist-info/METADATA
simplecoloredlogs-1.16.1.2026.dist-info/WHEEL
simplecoloredlogs-1.16.1.2026.dist-info/top_level.txt
simplecoloredlogs-1.16.1.2026.dist-info/RECORD
