Metadata-Version: 2.4
Name: SimpleColoredLogs
Version: 1.16.1.2026
Summary: Ein vollständiger, produktionsreifer Logger mit erweiterten Features für Python-Anwendungen und Discord Bots.
Author: OPPRO.NET Development, OPPRO.NET Network, LennyPegauOfficial117
License: MIT License
Project-URL: Homepage, https://github.com/Medicopter117/SimpleColoredLogs
Project-URL: Repository, https://github.com/Medicopter117/SimpleColoredLogs
Project-URL: Bug Tracker, https://github.com/Medicopter117/SimpleColoredLogs/issues
Keywords: logger,terminal,python,colored,discord,logs
Classifier: Programming Language :: Python :: 3
Classifier: License :: OSI Approved :: MIT License
Classifier: Operating System :: OS Independent
Classifier: Topic :: Software Development :: Libraries :: Python Modules
Classifier: Topic :: Utilities
Classifier: Intended Audience :: Developers
Requires-Python: >=3.7
License-File: LICENSE
Requires-Dist: colorama>=0.4.6
Requires-Dist: pathlib>=1.0.1
Dynamic: license-file
